cohesive_django/__init__.py
cohesive_django/auth.py
cohesive_marketplace_server_plugin_django-1.0.2.dist-info/LICENSE
cohesive_marketplace_server_plugin_django-1.0.2.dist-info/METADATA
cohesive_marketplace_server_plugin_django-1.0.2.dist-info/WHEEL
cohesive_marketplace_server_plugin_django-1.0.2.dist-info/top_level.txt
cohesive_marketplace_server_plugin_django-1.0.2.dist-info/RECORD
