Metadata-Version: 2.1
Name: cohesive-marketplace-server-plugin-django
Version: 1.0.2
Summary: Django plugin for the Cohesive Marketplace
Home-page: https://github.com/getcohesive/marketplace-server-plugin-django
Author: Cohesive
Author-email: Team Cohesive <contact@cohesive.so>
License: MIT
Project-URL: Source Code, https://github.com/getcohesive/marketplace-server-plugin-django
Keywords: cohesive api marketplace saas django
Classifier: Development Status :: 5 - Production/Stable
Classifier: Intended Audience :: Developers
Classifier: License :: OSI Approved :: MIT License
Classifier: Operating System :: OS Independent
Classifier: Programming Language :: Python
Classifier: Programming Language :: Python :: 3.7
Classifier: Programming Language :: Python :: 3.8
Classifier: Programming Language :: Python :: 3.9
Classifier: Programming Language :: Python :: 3.10
Classifier: Programming Language :: Python :: Implementation :: PyPy
Classifier: Topic :: Software Development :: Libraries :: Python Modules
Requires-Python: >=3.7
License-File: LICENSE
Requires-Dist: Django
Requires-Dist: cohesive-marketplace-server-sdk-python (==1.0.0)
